odoo/addons/hr_employee_id/README.rst
odoo/addons/hr_employee_id/__init__.py
odoo/addons/hr_employee_id/__manifest__.py
odoo/addons/hr_employee_id/data/hr_employee_sequence.xml
odoo/addons/hr_employee_id/i18n/ar.po
odoo/addons/hr_employee_id/i18n/cs_CZ.po
odoo/addons/hr_employee_id/i18n/de.po
odoo/addons/hr_employee_id/i18n/es.po
odoo/addons/hr_employee_id/i18n/fi.po
odoo/addons/hr_employee_id/i18n/fr.po
odoo/addons/hr_employee_id/i18n/hr.po
odoo/addons/hr_employee_id/i18n/hr_HR.po
odoo/addons/hr_employee_id/i18n/hr_employee_id.pot
odoo/addons/hr_employee_id/i18n/it.po
odoo/addons/hr_employee_id/i18n/lt.po
odoo/addons/hr_employee_id/i18n/nl_NL.po
odoo/addons/hr_employee_id/i18n/pt_BR.po
odoo/addons/hr_employee_id/i18n/ro.po
odoo/addons/hr_employee_id/i18n/sl.po
odoo/addons/hr_employee_id/models/__init__.py
odoo/addons/hr_employee_id/models/hr_employee.py
odoo/addons/hr_employee_id/models/res_company.py
odoo/addons/hr_employee_id/models/res_config_settings.py
odoo/addons/hr_employee_id/readme/CONFIGURE.md
odoo/addons/hr_employee_id/readme/CONTRIBUTORS.md
odoo/addons/hr_employee_id/readme/DESCRIPTION.md
odoo/addons/hr_employee_id/readme/INSTALL.md
odoo/addons/hr_employee_id/readme/ROADMAP.md
odoo/addons/hr_employee_id/readme/USAGE.md
odoo/addons/hr_employee_id/static/description/icon.png
odoo/addons/hr_employee_id/static/description/index.html
odoo/addons/hr_employee_id/tests/__init__.py
odoo/addons/hr_employee_id/tests/test_employee_id.py
odoo/addons/hr_employee_id/views/hr_employee_views.xml
odoo/addons/hr_employee_id/views/res_config_settings_views.xml
odoo_addon_hr_employee_id-18.0.1.0.0.2.dist-info/METADATA
odoo_addon_hr_employee_id-18.0.1.0.0.2.dist-info/WHEEL
odoo_addon_hr_employee_id-18.0.1.0.0.2.dist-info/top_level.txt
odoo_addon_hr_employee_id-18.0.1.0.0.2.dist-info/RECORD
